glue_etl/__init__.py
glue_etl/glue.py
glueetl-0.0.5.data/scripts/glueetl
glueetl-0.0.5.dist-info/LICENSE
glueetl-0.0.5.dist-info/METADATA
glueetl-0.0.5.dist-info/WHEEL
glueetl-0.0.5.dist-info/top_level.txt
glueetl-0.0.5.dist-info/RECORD
