Metadata-Version: 2.1
Name: glueetl
Version: 0.0.5
Summary: A command line tool to help deploy AWS Glue Jobs at ease :)
Home-page: https://github.com/ngocson2vn/glueetl
Author: Son Nguyen
Author-email: ngocson2vn@gmail.com
License: MIT
Platform: UNKNOWN
Classifier: Programming Language :: Python :: 3
Classifier: License :: OSI Approved :: MIT License
Classifier: Operating System :: OS Independent
Requires-Python: >=3.6
Requires-Dist: boto3
